{
  "total": 5336118,
  "page": 354,
  "pagesize": 100,
  "questions": [
    {
      "tags": [
        "jquery",
        "forms",
        "coldfusion"
      ],
      "answer_count": 0,
      "favorite_count": 0,
      "question_timeline_url": "/questions/17423009/timeline",
      "question_comments_url": "/questions/17423009/comments",
      "question_answers_url": "/questions/17423009/answers",
      "question_id": 17423009,
      "owner": {
        "user_id": 701839,
        "user_type": "registered",
        "display_name": "csber3",
        "reputation": 11,
        "email_hash": "78d8cfbd91b7c02825797d1b48772838"
      },
      "creation_date": 1372760238,
      "last_edit_date": 1372773517,
      "last_activity_date": 1372773517,
      "up_vote_count": 0,
      "down_vote_count": 0,
      "view_count": 39,
      "score": 0,
      "community_owned": false,
      "title": "jQuery posting to ColdFusion page failing on client machine"
    },
    {
      "tags": [
        "google-app-engine",
        "google-cloud-endpoints"
      ],
      "answer_count": 0,
      "favorite_count": 1,
      "question_timeline_url": "/questions/17427576/timeline",
      "question_comments_url": "/questions/17427576/comments",
      "question_answers_url": "/questions/17427576/answers",
      "question_id": 17427576,
      "owner": {
        "user_id": 979562,
        "user_type": "registered",
        "display_name": "Vincent Zhou",
        "reputation": 38,
        "email_hash": "94426b1841baa8a9750f3d4ae372a14b"
      },
      "creation_date": 1372773506,
      "last_activity_date": 1372773506,
      "up_vote_count": 0,
      "down_vote_count": 0,
      "view_count": 16,
      "score": 0,
      "community_owned": false,
      "title": "Google Cloud end point API doesn't update"
    },
    {
      "tags": [
        "java",
        "combobox",
        "foreach",
        "iterator",
        "javafx"
      ],
      "answer_count": 1,
      "accepted_answer_id": 17427449,
      "favorite_count": 0,
      "question_timeline_url": "/questions/17427124/timeline",
      "question_comments_url": "/questions/17427124/comments",
      "question_answers_url": "/questions/17427124/answers",
      "question_id": 17427124,
      "owner": {
        "user_id": 1517659,
        "user_type": "registered",
        "display_name": "Max Beikirch",
        "reputation": 533,
        "email_hash": "06e813c49334155892bd8bcd459d0145"
      },
      "creation_date": 1372772307,
      "last_activity_date": 1372773501,
      "up_vote_count": 0,
      "down_vote_count": 0,
      "view_count": 19,
      "score": 0,
      "community_owned": false,
      "title": "How to iterate through a JavaFX-combobox?"
    },
    {
      "tags": [
        "php",
        "mysql"
      ],
      "answer_count": 2,
      "accepted_answer_id": 17427349,
      "favorite_count": 0,
      "question_timeline_url": "/questions/17427233/timeline",
      "question_comments_url": "/questions/17427233/comments",
      "question_answers_url": "/questions/17427233/answers",
      "question_id": 17427233,
      "owner": {
        "user_id": 1973601,
        "user_type": "registered",
        "display_name": "SS Nath",
        "reputation": 15,
        "email_hash": "2985cefc2f68a6ae36e9c534116427fd"
      },
      "creation_date": 1372772587,
      "last_edit_date": 1372772873,
      "last_activity_date": 1372773489,
      "up_vote_count": 0,
      "down_vote_count": 0,
      "view_count": 43,
      "score": 0,
      "community_owned": false,
      "title": "how to display multiple images in php from database?"
    },
    {
      "tags": [
        "joomla"
      ],
      "answer_count": 2,
      "accepted_answer_id": 5065568,
      "favorite_count": 0,
      "question_timeline_url": "/questions/5037267/timeline",
      "question_comments_url": "/questions/5037267/comments",
      "question_answers_url": "/questions/5037267/answers",
      "question_id": 5037267,
      "owner": {
        "user_id": 622501,
        "user_type": "registered",
        "display_name": "gav_aus_web",
        "reputation": 37,
        "email_hash": "c08d78f29349352f7773f0e7430ba9cf"
      },
      "creation_date": 1297998826,
      "last_activity_date": 1372773486,
      "up_vote_count": 0,
      "down_vote_count": 0,
      "view_count": 555,
      "score": 0,
      "community_owned": false,
      "title": "Adding 'default text' to Joomla's extension 'Simple Email Form'"
    },
    {
      "tags": [
        "iphone",
        "ios",
        "objective-c",
        "nsstring"
      ],
      "answer_count": 2,
      "accepted_answer_id": 17422129,
      "favorite_count": 1,
      "closed_date": 1372767504,
      "closed_reason": "",
      "question_timeline_url": "/questions/17421900/timeline",
      "question_comments_url": "/questions/17421900/comments",
      "question_answers_url": "/questions/17421900/answers",
      "question_id": 17421900,
      "owner": {
        "user_id": 2465930,
        "user_type": "registered",
        "display_name": "Pawan Joshi",
        "reputation": 4,
        "email_hash": "65ff783a6a0459aeed7b9fa04882890d"
      },
      "creation_date": 1372757001,
      "last_edit_date": 1372773478,
      "last_activity_date": 1372773478,
      "up_vote_count": 1,
      "down_vote_count": 6,
      "view_count": 100,
      "score": -5,
      "community_owned": false,
      "title": "How to remove common letters in two Strings in iOS SDK?"
    },
    {
      "tags": [
        "c#",
        ".net",
        "silverlight",
        "web-applications"
      ],
      "answer_count": 1,
      "favorite_count": 0,
      "closed_date": 1372779027,
      "closed_reason": "",
      "question_timeline_url": "/questions/17427522/timeline",
      "question_comments_url": "/questions/17427522/comments",
      "question_answers_url": "/questions/17427522/answers",
      "question_id": 17427522,
      "owner": {
        "user_id": 1622374,
        "user_type": "registered",
        "display_name": "Tapho",
        "reputation": 1,
        "email_hash": "797bc8eb75b376a2012343cb4e39e610"
      },
      "creation_date": 1372773347,
      "last_activity_date": 1372773472,
      "up_vote_count": 0,
      "down_vote_count": 2,
      "view_count": 16,
      "score": -2,
      "community_owned": false,
      "title": "how to display .swf file on Silverlight Web Application?"
    },
    {
      "tags": [
        "mysql",
        "timestamp"
      ],
      "answer_count": 1,
      "favorite_count": 0,
      "question_timeline_url": "/questions/17427411/timeline",
      "question_comments_url": "/questions/17427411/comments",
      "question_answers_url": "/questions/17427411/answers",
      "question_id": 17427411,
      "owner": {
        "user_id": 1914757,
        "user_type": "registered",
        "display_name": "selvam",
        "reputation": 237,
        "email_hash": "de4f61dd0bddef5ef554f6844ea26ec5"
      },
      "creation_date": 1372773081,
      "last_edit_date": 1372773229,
      "last_activity_date": 1372773460,
      "up_vote_count": 0,
      "down_vote_count": 0,
      "view_count": 20,
      "score": 0,
      "community_owned": false,
      "title": "How to add time stamp values into MySQL database?"
    },
    {
      "tags": [
        "extjs"
      ],
      "answer_count": 3,
      "accepted_answer_id": 10601247,
      "favorite_count": 0,
      "question_timeline_url": "/questions/10387221/timeline",
      "question_comments_url": "/questions/10387221/comments",
      "question_answers_url": "/questions/10387221/answers",
      "question_id": 10387221,
      "owner": {
        "user_id": 403034,
        "user_type": "registered",
        "display_name": "Leo",
        "reputation": 79,
        "email_hash": "ed919dd67e9d8aedc67989430d140b74"
      },
      "creation_date": 1335803781,
      "last_activity_date": 1372773454,
      "up_vote_count": 2,
      "down_vote_count": 0,
      "view_count": 690,
      "score": 2,
      "community_owned": false,
      "title": "Timeout in Ext Direct"
    },
    {
      "tags": [
        "php",
        "sqlite",
        "pdo",
        "prepared-statement",
        "prepare"
      ],
      "answer_count": 1,
      "accepted_answer_id": 17408356,
      "favorite_count": 0,
      "question_timeline_url": "/questions/17408307/timeline",
      "question_comments_url": "/questions/17408307/comments",
      "question_answers_url": "/questions/17408307/answers",
      "question_id": 17408307,
      "owner": {
        "user_id": 1062690,
        "user_type": "registered",
        "display_name": "jsmith6",
        "reputation": 24,
        "email_hash": "25c31fc49bf6aced96b23f8fd0c6dc58"
      },
      "creation_date": 1372692871,
      "last_edit_date": 1372773443,
      "last_activity_date": 1372773443,
      "up_vote_count": 1,
      "down_vote_count": 0,
      "view_count": 25,
      "score": 1,
      "community_owned": false,
      "title": "SELECT WHERE with PDO prepare in PHP"
    },
    {
      "tags": [
        "types",
        "module",
        "include",
        "ocaml"
      ],
      "answer_count": 2,
      "accepted_answer_id": 17427559,
      "favorite_count": 1,
      "question_timeline_url": "/questions/17414523/timeline",
      "question_comments_url": "/questions/17414523/comments",
      "question_answers_url": "/questions/17414523/answers",
      "question_id": 17414523,
      "owner": {
        "user_id": 2138090,
        "user_type": "registered",
        "display_name": "Olle Härstedt",
        "reputation": 194,
        "email_hash": "c5632cd3c050c54e0d01e5b7631da6a3"
      },
      "creation_date": 1372716813,
      "last_activity_date": 1372773440,
      "up_vote_count": 5,
      "down_vote_count": 0,
      "view_count": 61,
      "score": 5,
      "community_owned": false,
      "title": "Including module, coercing"
    },
    {
      "tags": [
        "javascript",
        "facebook",
        "facebook-graph-api"
      ],
      "answer_count": 0,
      "favorite_count": 1,
      "question_timeline_url": "/questions/14064809/timeline",
      "question_comments_url": "/questions/14064809/comments",
      "question_answers_url": "/questions/14064809/answers",
      "question_id": 14064809,
      "owner": {
        "user_id": 1403248,
        "user_type": "registered",
        "display_name": "Ananda Kumar",
        "reputation": 19,
        "email_hash": "59de3ad997b191f7b941ecacc9a09f47"
      },
      "creation_date": 1356670928,
      "last_edit_date": 1356671479,
      "last_activity_date": 1372773440,
      "up_vote_count": 0,
      "down_vote_count": 0,
      "view_count": 116,
      "score": 0,
      "community_owned": false,
      "title": "Facebook video Upload"
    },
    {
      "tags": [
        "excel"
      ],
      "answer_count": 2,
      "accepted_answer_id": 17427555,
      "favorite_count": 1,
      "closed_date": 1372813936,
      "closed_reason": "",
      "question_timeline_url": "/questions/17425793/timeline",
      "question_comments_url": "/questions/17425793/comments",
      "question_answers_url": "/questions/17425793/answers",
      "question_id": 17425793,
      "owner": {
        "user_id": 577805,
        "user_type": "registered",
        "display_name": "Shapper",
        "reputation": 348,
        "email_hash": "dbbe0a475e6a151f0595b83e55475f34"
      },
      "creation_date": 1372768493,
      "last_activity_date": 1372773434,
      "up_vote_count": 0,
      "down_vote_count": 1,
      "view_count": 22,
      "score": -1,
      "community_owned": false,
      "title": "DSUM - Complex Criteria"
    },
    {
      "tags": [
        "ruby-on-rails",
        "svn",
        "redmine",
        "redmine-plugins"
      ],
      "answer_count": 0,
      "favorite_count": 0,
      "question_timeline_url": "/questions/17427553/timeline",
      "question_comments_url": "/questions/17427553/comments",
      "question_answers_url": "/questions/17427553/answers",
      "question_id": 17427553,
      "owner": {
        "user_id": 2509131,
        "user_type": "registered",
        "display_name": "A.L.",
        "reputation": 1,
        "email_hash": "1f7ba31ccd3c7f093ac16cf2a2bef401"
      },
      "creation_date": 1372773426,
      "last_activity_date": 1372773426,
      "up_vote_count": 0,
      "down_vote_count": 0,
      "view_count": 8,
      "score": 0,
      "community_owned": false,
      "title": "Redmine plug-in development with persistent svn-connection"
    },
    {
      "tags": [
        "jquery",
        "jqgrid"
      ],
      "answer_count": 1,
      "accepted_answer_id": 17427158,
      "favorite_count": 0,
      "question_timeline_url": "/questions/17426873/timeline",
      "question_comments_url": "/questions/17426873/comments",
      "question_answers_url": "/questions/17426873/answers",
      "question_id": 17426873,
      "owner": {
        "user_id": 1129960,
        "user_type": "registered",
        "display_name": "ZSH",
        "reputation": 53,
        "email_hash": "069378c3e7277339948efc8fe256d81e"
      },
      "creation_date": 1372771591,
      "last_edit_date": 1372773424,
      "last_activity_date": 1372773424,
      "up_vote_count": 0,
      "down_vote_count": 0,
      "view_count": 17,
      "score": 0,
      "community_owned": false,
      "title": "Multiselect checked change by condition"
    },
    {
      "tags": [
        "python",
        "numpy",
        "scipy",
        "sparse-matrix",
        "theano"
      ],
      "answer_count": 2,
      "favorite_count": 0,
      "question_timeline_url": "/questions/17426742/timeline",
      "question_comments_url": "/questions/17426742/comments",
      "question_answers_url": "/questions/17426742/answers",
      "question_id": 17426742,
      "owner": {
        "user_id": 2542699,
        "user_type": "registered",
        "display_name": "Bhanu",
        "reputation": 16,
        "email_hash": "9790635033ea8b42acac60d525fc004b"
      },
      "creation_date": 1372771251,
      "last_edit_date": 1372771859,
      "last_activity_date": 1372773421,
      "up_vote_count": 3,
      "down_vote_count": 0,
      "view_count": 40,
      "score": 3,
      "community_owned": false,
      "title": "How to calculate (1 - SparseMatrix) of a huge sparse matrix?"
    },
    {
      "tags": [
        "ios",
        "xcode",
        "core-graphics",
        "face-detection"
      ],
      "answer_count": 3,
      "accepted_answer_id": 9422678,
      "favorite_count": 3,
      "question_timeline_url": "/questions/9420188/timeline",
      "question_comments_url": "/questions/9420188/comments",
      "question_answers_url": "/questions/9420188/answers",
      "question_id": 9420188,
      "owner": {
        "user_id": 722,
        "user_type": "registered",
        "display_name": "Tim Sullivan",
        "reputation": 9162,
        "email_hash": "b3af5dc666dd2a558ea4fde3b8e24c65"
      },
      "creation_date": 1330026667,
      "last_activity_date": 1372773421,
      "up_vote_count": 4,
      "down_vote_count": 0,
      "view_count": 955,
      "score": 4,
      "community_owned": false,
      "title": "UIImage face detection"
    },
    {
      "tags": [
        "linux-kernel",
        "linux-device-driver"
      ],
      "answer_count": 1,
      "accepted_answer_id": 17427549,
      "favorite_count": 1,
      "question_timeline_url": "/questions/17400957/timeline",
      "question_comments_url": "/questions/17400957/comments",
      "question_answers_url": "/questions/17400957/answers",
      "question_id": 17400957,
      "owner": {
        "user_id": 1518516,
        "user_type": "registered",
        "display_name": "kzs",
        "reputation": 130,
        "email_hash": "65783b7260e0e49601d1f864eb668fba"
      },
      "creation_date": 1372670200,
      "last_activity_date": 1372773417,
      "up_vote_count": 0,
      "down_vote_count": 0,
      "view_count": 12,
      "score": 0,
      "community_owned": false,
      "title": "What is the difference between using gpio_tlmm_config and gpio_request + gpio_direction_input/output?"
    },
    {
      "tags": [
        "ssh"
      ],
      "answer_count": 0,
      "favorite_count": 0,
      "closed_date": 1372783022,
      "closed_reason": "",
      "question_timeline_url": "/questions/17427547/timeline",
      "question_comments_url": "/questions/17427547/comments",
      "question_answers_url": "/questions/17427547/answers",
      "question_id": 17427547,
      "owner": {
        "user_id": 2542893,
        "user_type": "registered",
        "display_name": "user2542893",
        "reputation": 1,
        "email_hash": "cac2d983642855f1dd704b4eb6145faf"
      },
      "creation_date": 1372773415,
      "last_activity_date": 1372773415,
      "up_vote_count": 0,
      "down_vote_count": 2,
      "view_count": 9,
      "score": -2,
      "community_owned": false,
      "title": "In SSH Tectia Windows 7"
    },
    {
      "tags": [
        "database",
        "list",
        "grails",
        "gsp"
      ],
      "answer_count": 2,
      "accepted_answer_id": 17427144,
      "favorite_count": 0,
      "question_timeline_url": "/questions/17426953/timeline",
      "question_comments_url": "/questions/17426953/comments",
      "question_answers_url": "/questions/17426953/answers",
      "question_id": 17426953,
      "owner": {
        "user_id": 1537580,
        "user_type": "registered",
        "display_name": "FrancescoDS",
        "reputation": 25,
        "email_hash": "87d3962ab267db8dfeed7454448b0090"
      },
      "creation_date": 1372771837,
      "last_activity_date": 1372773413,
      "up_vote_count": 0,
      "down_vote_count": 0,
      "view_count": 29,
      "score": 0,
      "community_owned": false,
      "title": "grails: show list of elements from database in gsp"
    },
    {
      "tags": [
        "xml",
        "windows-phone-7"
      ],
      "answer_count": 1,
      "accepted_answer_id": 17427546,
      "favorite_count": 0,
      "question_timeline_url": "/questions/17422395/timeline",
      "question_comments_url": "/questions/17422395/comments",
      "question_answers_url": "/questions/17422395/answers",
      "question_id": 17422395,
      "owner": {
        "user_id": 1514682,
        "user_type": "registered",
        "display_name": "Khayam Gondal",
        "reputation": 81,
        "email_hash": "8c077d0e2558ba773a8ab1d7300859f4"
      },
      "creation_date": 1372758477,
      "last_edit_date": 1372765178,
      "last_activity_date": 1372773410,
      "up_vote_count": 0,
      "down_vote_count": 0,
      "view_count": 11,
      "score": 0,
      "community_owned": false,
      "title": "Reading and updating specific child of xml"
    },
    {
      "tags": [
        "visual-studio-2008",
        "reporting-services",
        "ssrs-2008"
      ],
      "answer_count": 0,
      "favorite_count": 0,
      "question_timeline_url": "/questions/17427542/timeline",
      "question_comments_url": "/questions/17427542/comments",
      "question_answers_url": "/questions/17427542/answers",
      "question_id": 17427542,
      "owner": {
        "user_id": 347804,
        "user_type": "registered",
        "display_name": "Jack",
        "reputation": 6,
        "email_hash": "2965193680f8266d05258f7a5ac777bf"
      },
      "creation_date": 1372773400,
      "last_activity_date": 1372773400,
      "up_vote_count": 0,
      "down_vote_count": 0,
      "view_count": 8,
      "score": 0,
      "community_owned": false,
      "title": "Error opening reporting project in Visual Studio 2008"
    },
    {
      "tags": [
        "c#",
        "sql",
        "stored-procedures",
        "app-config",
        "transactionscope"
      ],
      "answer_count": 5,
      "favorite_count": 3,
      "question_timeline_url": "/questions/6402031/timeline",
      "question_comments_url": "/questions/6402031/comments",
      "question_answers_url": "/questions/6402031/answers",
      "question_id": 6402031,
      "owner": {
        "user_id": 436862,
        "user_type": "registered",
        "display_name": "user436862",
        "reputation": 88,
        "email_hash": "29c6be7e132e3e01399831bd1432295e"
      },
      "creation_date": 1308481925,
      "last_activity_date": 1372773389,
      "up_vote_count": 5,
      "down_vote_count": 0,
      "view_count": 6658,
      "score": 5,
      "community_owned": false,
      "title": "TransactionScope maximumTimeout"
    },
    {
      "tags": [
        "java",
        "jsf",
        "jsf-2",
        "uirepeat"
      ],
      "answer_count": 2,
      "favorite_count": 0,
      "question_timeline_url": "/questions/17427090/timeline",
      "question_comments_url": "/questions/17427090/comments",
      "question_answers_url": "/questions/17427090/answers",
      "question_id": 17427090,
      "owner": {
        "user_id": 712183,
        "user_type": "registered",
        "display_name": "Ray",
        "reputation": 418,
        "email_hash": "dd313494dc1c8d0dcf04b889de4f0878"
      },
      "creation_date": 1372772229,
      "last_edit_date": 1372772731,
      "last_activity_date": 1372773381,
      "up_vote_count": 0,
      "down_vote_count": 0,
      "view_count": 24,
      "score": 0,
      "community_owned": false,
      "title": "Replace c:foreach on ui:repeat"
    },
    {
      "tags": [
        "c#",
        "wpf",
        "user-interface",
        "line",
        "draw"
      ],
      "answer_count": 1,
      "favorite_count": 0,
      "question_timeline_url": "/questions/16340032/timeline",
      "question_comments_url": "/questions/16340032/comments",
      "question_answers_url": "/questions/16340032/answers",
      "question_id": 16340032,
      "owner": {
        "user_id": 2261524,
        "user_type": "registered",
        "display_name": "user2261524",
        "reputation": 125,
        "email_hash": "fceae20ff1e46a414940a29b143ae506"
      },
      "creation_date": 1367503168,
      "last_edit_date": 1372773380,
      "last_activity_date": 1372773380,
      "up_vote_count": 0,
      "down_vote_count": 0,
      "view_count": 56,
      "score": 0,
      "community_owned": false,
      "title": "C# canvas going overpainted"
    },
    {
      "tags": [
        "android",
        "textview"
      ],
      "answer_count": 2,
      "accepted_answer_id": 17425137,
      "favorite_count": 0,
      "question_timeline_url": "/questions/17424873/timeline",
      "question_comments_url": "/questions/17424873/comments",
      "question_answers_url": "/questions/17424873/answers",
      "question_id": 17424873,
      "owner": {
        "user_id": 2000012,
        "user_type": "registered",
        "display_name": "Teifi",
        "reputation": 469,
        "email_hash": "3d8760f7f1758059fb456924b6b21cdc"
      },
      "creation_date": 1372765864,
      "last_activity_date": 1372773377,
      "up_vote_count": 0,
      "down_vote_count": 1,
      "view_count": 46,
      "score": -1,
      "community_owned": false,
      "title": "InputType = PersonName?"
    },
    {
      "tags": [
        "ruby-on-rails",
        "view",
        "controller"
      ],
      "answer_count": 1,
      "accepted_answer_id": 17427531,
      "favorite_count": 0,
      "question_timeline_url": "/questions/17427496/timeline",
      "question_comments_url": "/questions/17427496/comments",
      "question_answers_url": "/questions/17427496/answers",
      "question_id": 17427496,
      "owner": {
        "user_id": 2542907,
        "user_type": "registered",
        "display_name": "zee klon",
        "reputation": 20,
        "email_hash": "2f31ecd2e27fc702690f0e899d0f11d7"
      },
      "creation_date": 1372773288,
      "last_activity_date": 1372773370,
      "up_vote_count": 1,
      "down_vote_count": 2,
      "view_count": 21,
      "score": -1,
      "community_owned": false,
      "title": "Call Controller Action from a View without changing the page"
    },
    {
      "tags": [
        "yii",
        "yii-extensions"
      ],
      "answer_count": 0,
      "favorite_count": 0,
      "question_timeline_url": "/questions/17427526/timeline",
      "question_comments_url": "/questions/17427526/comments",
      "question_answers_url": "/questions/17427526/answers",
      "question_id": 17427526,
      "owner": {
        "user_id": 2206911,
        "user_type": "registered",
        "display_name": "user2206911",
        "reputation": 10,
        "email_hash": "39aa5fc21ce8ab6bef13c205102906c8"
      },
      "creation_date": 1372773363,
      "last_activity_date": 1372773363,
      "up_vote_count": 0,
      "down_vote_count": 0,
      "view_count": 11,
      "score": 0,
      "community_owned": false,
      "title": "Yii framework and API for iphone apps"
    },
    {
      "tags": [
        ".net",
        "web-services",
        "service-reference"
      ],
      "answer_count": 0,
      "favorite_count": 0,
      "question_timeline_url": "/questions/17427017/timeline",
      "question_comments_url": "/questions/17427017/comments",
      "question_answers_url": "/questions/17427017/answers",
      "question_id": 17427017,
      "owner": {
        "user_id": 1069816,
        "user_type": "registered",
        "display_name": "user1069816",
        "reputation": 61,
        "email_hash": "580d9581ea680e8b1081645d0a1348cc"
      },
      "creation_date": 1372771999,
      "last_edit_date": 1372773359,
      "last_activity_date": 1372773359,
      "up_vote_count": 0,
      "down_vote_count": 0,
      "view_count": 40,
      "score": 0,
      "community_owned": false,
      "title": "What is the overhead in using a .NET Service Reference to call a web service?"
    },
    {
      "tags": [
        "java",
        "memory",
        "map",
        "hashmap"
      ],
      "answer_count": 1,
      "favorite_count": 0,
      "closed_date": 1372773408,
      "closed_reason": "",
      "question_timeline_url": "/questions/17427424/timeline",
      "question_comments_url": "/questions/17427424/comments",
      "question_answers_url": "/questions/17427424/answers",
      "question_id": 17427424,
      "owner": {
        "user_id": 2533312,
        "user_type": "registered",
        "display_name": "Ankita",
        "reputation": 12,
        "email_hash": "5d55da9749fcf887f5f95fde705eaedb"
      },
      "creation_date": 1372773113,
      "last_activity_date": 1372773337,
      "up_vote_count": 1,
      "down_vote_count": 2,
      "view_count": 39,
      "score": -1,
      "community_owned": false,
      "title": "How to memory map a hashmap to a file"
    },
    {
      "tags": [
        "visual-c++",
        "visual-studio-2012",
        "tfs"
      ],
      "answer_count": 0,
      "favorite_count": 0,
      "question_timeline_url": "/questions/17427513/timeline",
      "question_comments_url": "/questions/17427513/comments",
      "question_answers_url": "/questions/17427513/answers",
      "question_id": 17427513,
      "owner": {
        "user_id": 285632,
        "user_type": "registered",
        "display_name": "Pimenta",
        "reputation": 81,
        "email_hash": "199da6e4def0e3e9686d51858e97fc83"
      },
      "creation_date": 1372773333,
      "last_activity_date": 1372773333,
      "up_vote_count": 0,
      "down_vote_count": 0,
      "view_count": 7,
      "score": 0,
      "community_owned": false,
      "title": "VS2012: Project \"Property pages\" is displaying \"References\" window without configuration options"
    },
    {
      "tags": [
        "c#",
        ".net",
        "wpf",
        "c#-4.0",
        "mvvm"
      ],
      "answer_count": 1,
      "accepted_answer_id": 17421439,
      "favorite_count": 0,
      "question_timeline_url": "/questions/17416873/timeline",
      "question_comments_url": "/questions/17416873/comments",
      "question_answers_url": "/questions/17416873/answers",
      "question_id": 17416873,
      "owner": {
        "user_id": 1183979,
        "user_type": "registered",
        "display_name": "Divine",
        "reputation": 596,
        "email_hash": "c6b7e4f2f578db48f37bf141e7819a57"
      },
      "creation_date": 1372735053,
      "last_edit_date": 1372773321,
      "last_activity_date": 1372773321,
      "up_vote_count": 1,
      "down_vote_count": 0,
      "view_count": 38,
      "score": 1,
      "community_owned": false,
      "title": "style in wpf when targetted only on textblock, also applies same style to button contents automatically"
    },
    {
      "tags": [
        "xml",
        "zip",
        "xlsx"
      ],
      "answer_count": 2,
      "accepted_answer_id": 11116875,
      "favorite_count": 0,
      "question_timeline_url": "/questions/11082278/timeline",
      "question_comments_url": "/questions/11082278/comments",
      "question_answers_url": "/questions/11082278/answers",
      "question_id": 11082278,
      "owner": {
        "user_id": 293317,
        "user_type": "registered",
        "display_name": "ufw",
        "reputation": 142,
        "email_hash": "85b615add199d1c0496d4a9e417ab100"
      },
      "creation_date": 1340020491,
      "last_edit_date": 1340023863,
      "last_activity_date": 1372773319,
      "up_vote_count": 4,
      "down_vote_count": 0,
      "view_count": 1026,
      "score": 4,
      "community_owned": false,
      "title": "How to properly assemble a valid xlsx file from its internal sub-components?"
    },
    {
      "tags": [
        "php",
        "html"
      ],
      "answer_count": 3,
      "favorite_count": 0,
      "question_timeline_url": "/questions/17426938/timeline",
      "question_comments_url": "/questions/17426938/comments",
      "question_answers_url": "/questions/17426938/answers",
      "question_id": 17426938,
      "owner": {
        "user_id": 2534211,
        "user_type": "registered",
        "display_name": "user2534211",
        "reputation": 1,
        "email_hash": "b5e2d96082bb80ad20eb39ff36d0a90a"
      },
      "creation_date": 1372771779,
      "last_edit_date": 1372772288,
      "last_activity_date": 1372773297,
      "up_vote_count": 0,
      "down_vote_count": 3,
      "view_count": 46,
      "score": -3,
      "community_owned": false,
      "title": "How to add HTML with PHP passing headers"
    },
    {
      "tags": [
        "paypal-adaptive-payments"
      ],
      "answer_count": 0,
      "favorite_count": 0,
      "question_timeline_url": "/questions/17427502/timeline",
      "question_comments_url": "/questions/17427502/comments",
      "question_answers_url": "/questions/17427502/answers",
      "question_id": 17427502,
      "owner": {
        "user_id": 2044482,
        "user_type": "registered",
        "display_name": "Ionu Costescu",
        "reputation": 1,
        "email_hash": "23e77309d008419e9fa1edf37003d194"
      },
      "creation_date": 1372773294,
      "last_activity_date": 1372773294,
      "up_vote_count": 0,
      "down_vote_count": 0,
      "view_count": 7,
      "score": 0,
      "community_owned": false,
      "title": "REFUNDED_PENDING meaning"
    },
    {
      "tags": [
        "android",
        "listview",
        "actionbarsherlock",
        "fragment"
      ],
      "answer_count": 2,
      "favorite_count": 0,
      "question_timeline_url": "/questions/13718141/timeline",
      "question_comments_url": "/questions/13718141/comments",
      "question_answers_url": "/questions/13718141/answers",
      "question_id": 13718141,
      "owner": {
        "user_id": 1304170,
        "user_type": "registered",
        "display_name": "Skip",
        "reputation": 18,
        "email_hash": "253ca73edf4b7976e4636b85fa10c359"
      },
      "creation_date": 1354691780,
      "last_activity_date": 1372773292,
      "up_vote_count": 1,
      "down_vote_count": 0,
      "view_count": 667,
      "score": 1,
      "community_owned": false,
      "title": "Custom ListView confusion with Fragments"
    },
    {
      "tags": [
        "java",
        "android",
        "eclipse",
        "flash",
        "air"
      ],
      "answer_count": 1,
      "favorite_count": 0,
      "question_timeline_url": "/questions/17426859/timeline",
      "question_comments_url": "/questions/17426859/comments",
      "question_answers_url": "/questions/17426859/answers",
      "question_id": 17426859,
      "owner": {
        "user_id": 2542747,
        "user_type": "registered",
        "display_name": "Souma Cherifa",
        "reputation": 1,
        "email_hash": "a19067e4d60ae5e3f2d6894eb3c8ce1d"
      },
      "creation_date": 1372771571,
      "last_activity_date": 1372773291,
      "up_vote_count": 0,
      "down_vote_count": 1,
      "view_count": 31,
      "score": -1,
      "community_owned": false,
      "title": "Android UI editor"
    },
    {
      "tags": [
        "java",
        "web",
        "yellow-pages"
      ],
      "answer_count": 1,
      "favorite_count": 0,
      "closed_date": 1372773470,
      "closed_reason": "",
      "question_timeline_url": "/questions/17426631/timeline",
      "question_comments_url": "/questions/17426631/comments",
      "question_answers_url": "/questions/17426631/answers",
      "question_id": 17426631,
      "owner": {
        "user_id": 2376945,
        "user_type": "registered",
        "display_name": "fxm",
        "reputation": 66,
        "email_hash": "b467754c7cc5226900f8b5d1903f52ea"
      },
      "creation_date": 1372770884,
      "last_edit_date": 1372771194,
      "last_activity_date": 1372773288,
      "up_vote_count": 0,
      "down_vote_count": 2,
      "view_count": 27,
      "score": -2,
      "community_owned": false,
      "title": "Accessing yellow pages datas in Java?"
    },
    {
      "tags": [
        "text",
        "python-2.7",
        "insert",
        "tkinter"
      ],
      "answer_count": 1,
      "favorite_count": 0,
      "question_timeline_url": "/questions/17425602/timeline",
      "question_comments_url": "/questions/17425602/comments",
      "question_answers_url": "/questions/17425602/answers",
      "question_id": 17425602,
      "owner": {
        "user_id": 2169447,
        "user_type": "registered",
        "display_name": "J.Olsson",
        "reputation": 40,
        "email_hash": "9ae14b41d96a9954547abb7a1189b29b"
      },
      "creation_date": 1372767967,
      "last_edit_date": 1372768298,
      "last_activity_date": 1372773288,
      "up_vote_count": 0,
      "down_vote_count": 0,
      "view_count": 13,
      "score": 0,
      "community_owned": false,
      "title": "Insert Text into Tkinter.Text, throws error"
    },
    {
      "tags": [
        "silverlight"
      ],
      "answer_count": 0,
      "favorite_count": 0,
      "question_timeline_url": "/questions/17426312/timeline",
      "question_comments_url": "/questions/17426312/comments",
      "question_answers_url": "/questions/17426312/answers",
      "question_id": 17426312,
      "owner": {
        "user_id": 1070412,
        "user_type": "registered",
        "display_name": "Grant H.",
        "reputation": 1149,
        "email_hash": "6d4216bdacceb1a1f104c16c7719c139"
      },
      "creation_date": 1372769949,
      "last_edit_date": 1372773277,
      "last_activity_date": 1372773277,
      "up_vote_count": 0,
      "down_vote_count": 0,
      "view_count": 7,
      "score": 0,
      "community_owned": false,
      "title": "Monitor Application Library Caching Download Progress"
    },
    {
      "tags": [
        "javascript",
        "highcharts"
      ],
      "answer_count": 1,
      "accepted_answer_id": 17426841,
      "favorite_count": 0,
      "question_timeline_url": "/questions/17426790/timeline",
      "question_comments_url": "/questions/17426790/comments",
      "question_answers_url": "/questions/17426790/answers",
      "question_id": 17426790,
      "owner": {
        "user_id": 2542310,
        "user_type": "registered",
        "display_name": "al123",
        "reputation": 58,
        "email_hash": "0abd6782e9f3858dc2f536814bdfc6cd"
      },
      "creation_date": 1372771386,
      "last_edit_date": 1372773272,
      "last_activity_date": 1372773272,
      "up_vote_count": 2,
      "down_vote_count": 0,
      "view_count": 32,
      "score": 2,
      "community_owned": false,
      "title": "adding more data in highchart"
    },
    {
      "tags": [
        "maven"
      ],
      "answer_count": 0,
      "favorite_count": 0,
      "question_timeline_url": "/questions/17427487/timeline",
      "question_comments_url": "/questions/17427487/comments",
      "question_answers_url": "/questions/17427487/answers",
      "question_id": 17427487,
      "owner": {
        "user_id": 191214,
        "user_type": "registered",
        "display_name": "april26",
        "reputation": 337,
        "email_hash": "e59e5ebf33e433aa32c3a0cc2a3c3fac"
      },
      "creation_date": 1372773270,
      "last_activity_date": 1372773270,
      "up_vote_count": 0,
      "down_vote_count": 0,
      "view_count": 11,
      "score": 0,
      "community_owned": false,
      "title": "Archetype is in repository but not found by either eclipse or commandline?"
    },
    {
      "tags": [
        "android",
        "textview",
        "preferences"
      ],
      "answer_count": 0,
      "favorite_count": 0,
      "question_timeline_url": "/questions/17427486/timeline",
      "question_comments_url": "/questions/17427486/comments",
      "question_answers_url": "/questions/17427486/answers",
      "question_id": 17427486,
      "owner": {
        "user_id": 2352679,
        "user_type": "registered",
        "display_name": "user2352679",
        "reputation": 8,
        "email_hash": "60c700e5042c3804867e10a38bf50bb5"
      },
      "creation_date": 1372773267,
      "last_activity_date": 1372773267,
      "up_vote_count": 0,
      "down_vote_count": 0,
      "view_count": 13,
      "score": 0,
      "community_owned": false,
      "title": "Edit TextView in Preference layout from main PreferenceActivity"
    },
    {
      "tags": [
        "javascript"
      ],
      "answer_count": 4,
      "accepted_answer_id": 17427283,
      "favorite_count": 0,
      "question_timeline_url": "/questions/17427202/timeline",
      "question_comments_url": "/questions/17427202/comments",
      "question_answers_url": "/questions/17427202/answers",
      "question_id": 17427202,
      "owner": {
        "user_id": 379008,
        "user_type": "registered",
        "display_name": "GibboK",
        "reputation": 5518,
        "email_hash": "662fb22e661f47132799538b89691afc"
      },
      "creation_date": 1372772492,
      "last_activity_date": 1372773267,
      "up_vote_count": 1,
      "down_vote_count": 0,
      "view_count": 43,
      "score": 1,
      "community_owned": false,
      "title": "How to add a document fragement to a div"
    },
    {
      "tags": [
        "ruby-on-rails",
        "ajax",
        "simple-form"
      ],
      "answer_count": 3,
      "accepted_answer_id": 10255270,
      "favorite_count": 0,
      "question_timeline_url": "/questions/10255198/timeline",
      "question_comments_url": "/questions/10255198/comments",
      "question_answers_url": "/questions/10255198/answers",
      "question_id": 10255198,
      "owner": {
        "user_id": 1092012,
        "user_type": "registered",
        "display_name": "Nathan",
        "reputation": 1086,
        "email_hash": "10370955d7505a5738d223e11015bfc4"
      },
      "creation_date": 1334969179,
      "last_activity_date": 1372773262,
      "up_vote_count": 2,
      "down_vote_count": 0,
      "view_count": 1257,
      "score": 2,
      "community_owned": false,
      "title": "Is there a way to submit ajax/json requests with simple_form for Rails"
    },
    {
      "tags": [
        "c#",
        "file",
        "io",
        "kinect"
      ],
      "answer_count": 1,
      "accepted_answer_id": 14805229,
      "favorite_count": 0,
      "question_timeline_url": "/questions/14804659/timeline",
      "question_comments_url": "/questions/14804659/comments",
      "question_answers_url": "/questions/14804659/answers",
      "question_id": 14804659,
      "owner": {
        "user_id": 1453738,
        "user_type": "registered",
        "display_name": "UsherTech",
        "reputation": 11,
        "email_hash": "4cb96d88d5cf012c09b6713cff120952"
      },
      "creation_date": 1360545679,
      "last_edit_date": 1360552043,
      "last_activity_date": 1372773262,
      "up_vote_count": 0,
      "down_vote_count": 0,
      "view_count": 191,
      "score": 0,
      "community_owned": false,
      "title": "Recording video/Image information in C# file size is huge"
    },
    {
      "tags": [
        "merge",
        "synchronization",
        "backup",
        "bidirectional"
      ],
      "answer_count": 1,
      "favorite_count": 0,
      "question_timeline_url": "/questions/9716785/timeline",
      "question_comments_url": "/questions/9716785/comments",
      "question_answers_url": "/questions/9716785/answers",
      "question_id": 9716785,
      "owner": {
        "user_id": 1069375,
        "user_type": "registered",
        "display_name": "Marcos",
        "reputation": 751,
        "email_hash": "6235a867d68ca47947f2015c2eaf0552"
      },
      "creation_date": 1331802854,
      "last_activity_date": 1372773258,
      "up_vote_count": 1,
      "down_vote_count": 0,
      "view_count": 286,
      "score": 1,
      "community_owned": false,
      "title": "flexible merge command for unison to pick newer or older file?"
    },
    {
      "tags": [
        "php",
        "google-maps-api-3",
        "google-earth"
      ],
      "answer_count": 0,
      "favorite_count": 1,
      "question_timeline_url": "/questions/17427453/timeline",
      "question_comments_url": "/questions/17427453/comments",
      "question_answers_url": "/questions/17427453/answers",
      "question_id": 17427453,
      "owner": {
        "user_id": 1289928,
        "user_type": "registered",
        "display_name": "mer hardik",
        "reputation": 81,
        "email_hash": "9da5cb5068e0acafc4686a35f7a892c3"
      },
      "creation_date": 1372773187,
      "last_edit_date": 1372773252,
      "last_activity_date": 1372773252,
      "up_vote_count": 0,
      "down_vote_count": 0,
      "view_count": 12,
      "score": 0,
      "community_owned": false,
      "title": "showing google earth fully zoomed out and zoomin zoom out navigation"
    },
    {
      "tags": [
        "css",
        "footer"
      ],
      "answer_count": 2,
      "accepted_answer_id": 17427472,
      "favorite_count": 0,
      "question_timeline_url": "/questions/17369042/timeline",
      "question_comments_url": "/questions/17369042/comments",
      "question_answers_url": "/questions/17369042/answers",
      "question_id": 17369042,
      "owner": {
        "user_id": 1377961,
        "user_type": "registered",
        "display_name": "tony danza",
        "reputation": 59,
        "email_hash": "6ad8d5be9e5d687d4f695138a2a4c8e4"
      },
      "creation_date": 1372435555,
      "last_edit_date": 1372681764,
      "last_activity_date": 1372773247,
      "up_vote_count": 0,
      "down_vote_count": 0,
      "view_count": 44,
      "score": 0,
      "community_owned": false,
      "title": "footer height in css"
    },
    {
      "tags": [
        ".net",
        "asp-classic",
        "charts"
      ],
      "answer_count": 1,
      "favorite_count": 0,
      "question_timeline_url": "/questions/17427113/timeline",
      "question_comments_url": "/questions/17427113/comments",
      "question_answers_url": "/questions/17427113/answers",
      "question_id": 17427113,
      "owner": {
        "user_id": 2302944,
        "user_type": "registered",
        "display_name": "user2302944",
        "reputation": 1,
        "email_hash": "55d9a8a45cb17878df57d996b2e79b43"
      },
      "creation_date": 1372772272,
      "last_activity_date": 1372773245,
      "up_vote_count": 0,
      "down_vote_count": 0,
      "view_count": 8,
      "score": 0,
      "community_owned": false,
      "title": "How to export a chart to excel as a chart object"
    },
    {
      "tags": [
        "android"
      ],
      "answer_count": 7,
      "accepted_answer_id": 10795234,
      "favorite_count": 2,
      "question_timeline_url": "/questions/10795078/timeline",
      "question_comments_url": "/questions/10795078/comments",
      "question_answers_url": "/questions/10795078/answers",
      "question_id": 10795078,
      "owner": {
        "user_id": 739323,
        "user_type": "registered",
        "display_name": "Programmer",
        "reputation": 476,
        "email_hash": "d0494cd9421b032de23f705361f51aa2"
      },
      "creation_date": 1338277825,
      "last_activity_date": 1372773236,
      "up_vote_count": 9,
      "down_vote_count": 0,
      "view_count": 6131,
      "score": 9,
      "community_owned": false,
      "title": "Dialog with transparent background in Android"
    },
    {
      "tags": [
        "instagram"
      ],
      "answer_count": 1,
      "favorite_count": 0,
      "question_timeline_url": "/questions/17426597/timeline",
      "question_comments_url": "/questions/17426597/comments",
      "question_answers_url": "/questions/17426597/answers",
      "question_id": 17426597,
      "owner": {
        "user_id": 1722794,
        "user_type": "registered",
        "display_name": "Hugo",
        "reputation": 6,
        "email_hash": "0c9e53e918d4ce1d045b935a6cdf2d9a"
      },
      "creation_date": 1372770789,
      "last_activity_date": 1372773234,
      "up_vote_count": 0,
      "down_vote_count": 0,
      "view_count": 21,
      "score": 0,
      "community_owned": false,
      "title": "Instagram search by area"
    },
    {
      "tags": [
        "sql",
        "sql-server",
        "where-clause"
      ],
      "answer_count": 2,
      "accepted_answer_id": 17410758,
      "favorite_count": 0,
      "question_timeline_url": "/questions/17410573/timeline",
      "question_comments_url": "/questions/17410573/comments",
      "question_answers_url": "/questions/17410573/answers",
      "question_id": 17410573,
      "owner": {
        "user_id": 1616260,
        "user_type": "registered",
        "display_name": "Ruben Ravnå",
        "reputation": 3,
        "email_hash": "4e2e81f92a54ca7523145167f836d206"
      },
      "creation_date": 1372700981,
      "last_activity_date": 1372773233,
      "up_vote_count": 0,
      "down_vote_count": 0,
      "view_count": 27,
      "score": 0,
      "community_owned": false,
      "title": "Multiple statements in where clause, records newer than 3 weeks"
    },
    {
      "tags": [
        "c#",
        "c#-4.0",
        "task-parallel-library"
      ],
      "answer_count": 1,
      "accepted_answer_id": 17427348,
      "favorite_count": 2,
      "question_timeline_url": "/questions/17423194/timeline",
      "question_comments_url": "/questions/17423194/comments",
      "question_answers_url": "/questions/17423194/answers",
      "question_id": 17423194,
      "owner": {
        "user_id": 1307927,
        "user_type": "registered",
        "display_name": "Sriram B",
        "reputation": 63,
        "email_hash": "53ce53c40a8a29195d1a8bb627316f36"
      },
      "creation_date": 1372760826,
      "last_edit_date": 1372760877,
      "last_activity_date": 1372773229,
      "up_vote_count": 1,
      "down_vote_count": 0,
      "view_count": 20,
      "score": 1,
      "community_owned": false,
      "title": "Logging in proper order in Task Parallel Library scenario"
    },
    {
      "tags": [
        "asp.net",
        ".net",
        "asp.net-web-api"
      ],
      "answer_count": 1,
      "favorite_count": 0,
      "question_timeline_url": "/questions/17404373/timeline",
      "question_comments_url": "/questions/17404373/comments",
      "question_answers_url": "/questions/17404373/answers",
      "question_id": 17404373,
      "owner": {
        "user_id": 252959,
        "user_type": "registered",
        "display_name": "Martin Booth",
        "reputation": 3840,
        "email_hash": "e74d2e47a29887db15c2ef31221f66c1"
      },
      "creation_date": 1372681231,
      "last_activity_date": 1372773222,
      "up_vote_count": 1,
      "down_vote_count": 0,
      "view_count": 72,
      "score": 1,
      "community_owned": false,
      "title": "Visual studio 2013 preview SPA template"
    },
    {
      "tags": [
        "java",
        "authentication",
        "client",
        "kerberos",
        "required"
      ],
      "answer_count": 0,
      "favorite_count": 0,
      "question_timeline_url": "/questions/17427460/timeline",
      "question_comments_url": "/questions/17427460/comments",
      "question_answers_url": "/questions/17427460/answers",
      "question_id": 17427460,
      "owner": {
        "user_id": 332319,
        "user_type": "registered",
        "display_name": "Kjeld",
        "reputation": 14,
        "email_hash": "7363f480d8dab5fccc6f3692c4d631e0"
      },
      "creation_date": 1372773215,
      "last_activity_date": 1372773215,
      "up_vote_count": 0,
      "down_vote_count": 1,
      "view_count": 9,
      "score": -1,
      "community_owned": false,
      "title": "How to access website with Kerberos authentication mechanism using Java client"
    },
    {
      "tags": [
        "php",
        "html",
        "phpmyadmin"
      ],
      "answer_count": 2,
      "favorite_count": 0,
      "question_timeline_url": "/questions/17426723/timeline",
      "question_comments_url": "/questions/17426723/comments",
      "question_answers_url": "/questions/17426723/answers",
      "question_id": 17426723,
      "owner": {
        "user_id": 2538286,
        "user_type": "registered",
        "display_name": "ashy1234",
        "reputation": 3,
        "email_hash": "9eedfba96da42950335ddbbcb4039d92"
      },
      "creation_date": 1372771206,
      "last_activity_date": 1372773214,
      "up_vote_count": 0,
      "down_vote_count": 0,
      "view_count": 27,
      "score": 0,
      "community_owned": false,
      "title": "how to store the class object array value into database and reterieve theses value from the database"
    },
    {
      "tags": [
        "combinatorics"
      ],
      "answer_count": 0,
      "favorite_count": 0,
      "closed_date": 1372773214,
      "closed_reason": "",
      "question_timeline_url": "/questions/17425032/timeline",
      "question_comments_url": "/questions/17425032/comments",
      "question_answers_url": "/questions/17425032/answers",
      "question_id": 17425032,
      "locked_date": 1372773214,
      "owner": {
        "user_id": 2173429,
        "user_type": "registered",
        "display_name": "user2173429",
        "reputation": 1,
        "email_hash": "eba6857e7a170e23f3ace9b9a533507a"
      },
      "creation_date": 1372766306,
      "last_edit_date": 1372773198,
      "last_activity_date": 1372773201,
      "up_vote_count": 0,
      "down_vote_count": 0,
      "view_count": 36,
      "score": 0,
      "community_owned": false,
      "title": "Lottery tickets generation"
    },
    {
      "tags": [
        "arrays",
        "forms",
        "url",
        "printing"
      ],
      "answer_count": 1,
      "accepted_answer_id": 17427304,
      "favorite_count": 0,
      "question_timeline_url": "/questions/17427077/timeline",
      "question_comments_url": "/questions/17427077/comments",
      "question_answers_url": "/questions/17427077/answers",
      "question_id": 17427077,
      "owner": {
        "user_id": 2304434,
        "user_type": "registered",
        "display_name": "user2304434",
        "reputation": 5,
        "email_hash": "f72565fa8fb4ce70c9038a951bed7c03"
      },
      "creation_date": 1372772177,
      "last_activity_date": 1372773195,
      "up_vote_count": 0,
      "down_vote_count": 0,
      "view_count": 18,
      "score": 0,
      "community_owned": false,
      "title": "Loop Page Number in PHP"
    },
    {
      "tags": [
        "mysql",
        "random",
        "integer",
        "default"
      ],
      "answer_count": 2,
      "favorite_count": 0,
      "question_timeline_url": "/questions/17427236/timeline",
      "question_comments_url": "/questions/17427236/comments",
      "question_answers_url": "/questions/17427236/answers",
      "question_id": 17427236,
      "owner": {
        "user_id": 409958,
        "user_type": "registered",
        "display_name": "Dick Savagewood",
        "reputation": 1178,
        "email_hash": "59fd7d0c6376f48d02c98abb00d057c5"
      },
      "creation_date": 1372772598,
      "last_activity_date": 1372773193,
      "up_vote_count": 0,
      "down_vote_count": 0,
      "view_count": 23,
      "score": 0,
      "community_owned": false,
      "title": "mysql automatic random default integer value"
    },
    {
      "tags": [
        "ios",
        "objective-c",
        "uikit"
      ],
      "answer_count": 1,
      "accepted_answer_id": 17425199,
      "favorite_count": 0,
      "question_timeline_url": "/questions/17424207/timeline",
      "question_comments_url": "/questions/17424207/comments",
      "question_answers_url": "/questions/17424207/answers",
      "question_id": 17424207,
      "owner": {
        "user_id": 160149,
        "user_type": "registered",
        "display_name": "jonydep",
        "reputation": 202,
        "email_hash": "ee06835e17a71e6d8518c3e784e04c87"
      },
      "creation_date": 1372763985,
      "last_edit_date": 1372773187,
      "last_activity_date": 1372773187,
      "up_vote_count": 0,
      "down_vote_count": 0,
      "view_count": 58,
      "score": 0,
      "community_owned": false,
      "title": "UITextField resigns first responder when scrolling in UITableView isn't fast enough"
    },
    {
      "tags": [
        "java",
        "jpa"
      ],
      "answer_count": 2,
      "favorite_count": 0,
      "closed_date": 1372800891,
      "closed_reason": "",
      "question_timeline_url": "/questions/17425577/timeline",
      "question_comments_url": "/questions/17425577/comments",
      "question_answers_url": "/questions/17425577/answers",
      "question_id": 17425577,
      "owner": {
        "user_id": 2248600,
        "user_type": "registered",
        "display_name": "Mathew Rock",
        "reputation": 9,
        "email_hash": "ba49ce93881e901a5dee822bb755c401"
      },
      "creation_date": 1372767904,
      "last_edit_date": 1372769618,
      "last_activity_date": 1372773186,
      "up_vote_count": 0,
      "down_vote_count": 1,
      "view_count": 33,
      "score": -1,
      "community_owned": false,
      "title": "JPA select generate with relationship in columns"
    },
    {
      "tags": [
        "regex",
        ".htaccess",
        "redirect"
      ],
      "answer_count": 1,
      "accepted_answer_id": 17427451,
      "favorite_count": 0,
      "question_timeline_url": "/questions/17427190/timeline",
      "question_comments_url": "/questions/17427190/comments",
      "question_answers_url": "/questions/17427190/answers",
      "question_id": 17427190,
      "owner": {
        "user_id": 1563841,
        "user_type": "registered",
        "display_name": "nmford",
        "reputation": 49,
        "email_hash": "27a03a779b199f870a2846581eb70c5e"
      },
      "creation_date": 1372772475,
      "last_activity_date": 1372773186,
      "up_vote_count": 1,
      "down_vote_count": 0,
      "view_count": 17,
      "score": 1,
      "community_owned": false,
      "title": "RedirectMatch Regex only working on some browsers/machines"
    },
    {
      "tags": [
        "jquery"
      ],
      "answer_count": 1,
      "accepted_answer_id": 17427248,
      "favorite_count": 0,
      "closed_date": 1372772933,
      "closed_reason": "",
      "question_timeline_url": "/questions/17427206/timeline",
      "question_comments_url": "/questions/17427206/comments",
      "question_answers_url": "/questions/17427206/answers",
      "question_id": 17427206,
      "owner": {
        "user_id": 2143820,
        "user_type": "registered",
        "display_name": "Lee Banks",
        "reputation": 8,
        "email_hash": "a328e75b288d9e4149c5bc58061394a4"
      },
      "creation_date": 1372772498,
      "last_edit_date": 1372772889,
      "last_activity_date": 1372773176,
      "up_vote_count": 1,
      "down_vote_count": 0,
      "view_count": 41,
      "score": 1,
      "community_owned": false,
      "title": "Outputting to 2 decimal places"
    },
    {
      "tags": [
        "jsf",
        "java-ee"
      ],
      "answer_count": 1,
      "favorite_count": 0,
      "question_timeline_url": "/questions/17427288/timeline",
      "question_comments_url": "/questions/17427288/comments",
      "question_answers_url": "/questions/17427288/answers",
      "question_id": 17427288,
      "owner": {
        "user_id": 2439467,
        "user_type": "registered",
        "display_name": "enricko",
        "reputation": 14,
        "email_hash": "b0e973da557d9059cb73bd05f400973b"
      },
      "creation_date": 1372772729,
      "last_activity_date": 1372773176,
      "up_vote_count": 0,
      "down_vote_count": 0,
      "view_count": 10,
      "score": 0,
      "community_owned": false,
      "title": "Managed property between SessionScoped ManagedBeans"
    },
    {
      "tags": [
        "java",
        "swing"
      ],
      "answer_count": 2,
      "favorite_count": 0,
      "question_timeline_url": "/questions/10463903/timeline",
      "question_comments_url": "/questions/10463903/comments",
      "question_answers_url": "/questions/10463903/answers",
      "question_id": 10463903,
      "owner": {
        "user_id": 1210237,
        "user_type": "registered",
        "display_name": "Lourin",
        "reputation": 85,
        "email_hash": "c7dc4137e7f99955a1a4834083ce8b15"
      },
      "creation_date": 1336236315,
      "last_edit_date": 1336238539,
      "last_activity_date": 1372773169,
      "up_vote_count": 0,
      "down_vote_count": 0,
      "view_count": 630,
      "score": 0,
      "community_owned": false,
      "title": "using JDirectoryChooser in java swing"
    },
    {
      "tags": [
        "sip",
        "voip",
        "embedded-linux",
        "gsm",
        "at-command"
      ],
      "answer_count": 2,
      "favorite_count": 0,
      "question_timeline_url": "/questions/10300547/timeline",
      "question_comments_url": "/questions/10300547/comments",
      "question_answers_url": "/questions/10300547/answers",
      "question_id": 10300547,
      "owner": {
        "user_id": 1225421,
        "user_type": "registered",
        "display_name": "Alex Pandrea",
        "reputation": 34,
        "email_hash": "50a8c3e33d6e17d8c20c2cf6a34d34a4"
      },
      "creation_date": 1335279474,
      "last_edit_date": 1335533040,
      "last_activity_date": 1372773163,
      "up_vote_count": 2,
      "down_vote_count": 0,
      "view_count": 799,
      "score": 2,
      "community_owned": false,
      "title": "How to control modems inside a GoIP gateway with AT commands"
    },
    {
      "tags": [
        "android",
        "application"
      ],
      "answer_count": 2,
      "favorite_count": 0,
      "question_timeline_url": "/questions/17425481/timeline",
      "question_comments_url": "/questions/17425481/comments",
      "question_answers_url": "/questions/17425481/answers",
      "question_id": 17425481,
      "owner": {
        "user_id": 2521549,
        "user_type": "registered",
        "display_name": "Stefan Rafa",
        "reputation": 6,
        "email_hash": "f1b948310b4be4e5c4e8283fc45a86ca"
      },
      "creation_date": 1372767611,
      "last_edit_date": 1372773161,
      "last_activity_date": 1372773161,
      "up_vote_count": 0,
      "down_vote_count": 0,
      "view_count": 53,
      "score": 0,
      "community_owned": false,
      "title": "Android app error “Unfortunately App has Stopped”"
    },
    {
      "tags": [
        "linux",
        "embedded-linux",
        "crosstool-ng"
      ],
      "answer_count": 0,
      "favorite_count": 0,
      "question_timeline_url": "/questions/17427440/timeline",
      "question_comments_url": "/questions/17427440/comments",
      "question_answers_url": "/questions/17427440/answers",
      "question_id": 17427440,
      "owner": {
        "user_id": 983195,
        "user_type": "registered",
        "display_name": "user983195",
        "reputation": 24,
        "email_hash": "5e2dbfe48639a0540f886da54ae05d63"
      },
      "creation_date": 1372773155,
      "last_activity_date": 1372773155,
      "up_vote_count": 0,
      "down_vote_count": 0,
      "view_count": 10,
      "score": 0,
      "community_owned": false,
      "title": "Crosstool-ng build error"
    },
    {
      "tags": [
        "templates",
        "module",
        "admin",
        "prestashop"
      ],
      "answer_count": 2,
      "favorite_count": 0,
      "question_timeline_url": "/questions/17412838/timeline",
      "question_comments_url": "/questions/17412838/comments",
      "question_answers_url": "/questions/17412838/answers",
      "question_id": 17412838,
      "owner": {
        "user_id": 1393876,
        "user_type": "registered",
        "display_name": "user1393876",
        "reputation": 13,
        "email_hash": "b876afb5d0e9a666095527965b436205"
      },
      "creation_date": 1372709551,
      "last_activity_date": 1372773153,
      "up_vote_count": 0,
      "down_vote_count": 0,
      "view_count": 17,
      "score": 0,
      "community_owned": false,
      "title": "Custom Prestashop Admin Module"
    },
    {
      "tags": [
        "java",
        "jsf",
        "servlets",
        "servlet-filters"
      ],
      "answer_count": 1,
      "favorite_count": 0,
      "question_timeline_url": "/questions/17426872/timeline",
      "question_comments_url": "/questions/17426872/comments",
      "question_answers_url": "/questions/17426872/answers",
      "question_id": 17426872,
      "owner": {
        "user_id": 2498461,
        "user_type": "registered",
        "display_name": "rubaka",
        "reputation": 3,
        "email_hash": "0b64f1b175d6399536e84f984377cfd8"
      },
      "creation_date": 1372771589,
      "last_edit_date": 1372773153,
      "last_activity_date": 1372773153,
      "up_vote_count": 0,
      "down_vote_count": 0,
      "view_count": 40,
      "score": 0,
      "community_owned": false,
      "title": "Servlet Filter not working"
    },
    {
      "tags": [
        "jqgrid"
      ],
      "answer_count": 1,
      "accepted_answer_id": 17427432,
      "favorite_count": 0,
      "question_timeline_url": "/questions/17426976/timeline",
      "question_comments_url": "/questions/17426976/comments",
      "question_answers_url": "/questions/17426976/answers",
      "question_id": 17426976,
      "owner": {
        "user_id": 1872284,
        "user_type": "registered",
        "display_name": "Giacomo Savioli",
        "reputation": 16,
        "email_hash": "a586d9072af7a481d19bda9c0de93a5d"
      },
      "creation_date": 1372771878,
      "last_edit_date": 1372772890,
      "last_activity_date": 1372773146,
      "up_vote_count": 0,
      "down_vote_count": 0,
      "view_count": 13,
      "score": 0,
      "community_owned": false,
      "title": "How to sort numeric column in jqgrid"
    },
    {
      "tags": [
        "regex",
        "perl",
        "parsing"
      ],
      "answer_count": 1,
      "accepted_answer_id": 17426669,
      "favorite_count": 1,
      "question_timeline_url": "/questions/17426454/timeline",
      "question_comments_url": "/questions/17426454/comments",
      "question_answers_url": "/questions/17426454/answers",
      "question_id": 17426454,
      "owner": {
        "user_id": 1338584,
        "user_type": "registered",
        "display_name": "shaun",
        "reputation": 62,
        "email_hash": "58264bf7ce5ad8f1768197c573d1f43e"
      },
      "creation_date": 1372770385,
      "last_edit_date": 1372773141,
      "last_activity_date": 1372773141,
      "up_vote_count": 5,
      "down_vote_count": 0,
      "view_count": 56,
      "score": 5,
      "community_owned": false,
      "title": "Splitting a string containing space-delimited \"key=value\" pairs when the value can also contain space"
    },
    {
      "tags": [
        "nlp",
        "data-mining",
        "lda"
      ],
      "answer_count": 0,
      "favorite_count": 1,
      "question_timeline_url": "/questions/17421887/timeline",
      "question_comments_url": "/questions/17421887/comments",
      "question_answers_url": "/questions/17421887/answers",
      "question_id": 17421887,
      "owner": {
        "user_id": 1213192,
        "user_type": "registered",
        "display_name": "wwssttt",
        "reputation": 57,
        "email_hash": "99c5e9fa27c8603dc89adb393fe3cdd1"
      },
      "creation_date": 1372756964,
      "last_edit_date": 1372773141,
      "last_activity_date": 1372773141,
      "up_vote_count": 1,
      "down_vote_count": 0,
      "view_count": 18,
      "score": 1,
      "community_owned": false,
      "title": "how to determine the number of topics for LDA?"
    },
    {
      "tags": [
        "asp.net-mvc",
        "visual-studio",
        "web-config",
        "iis-express"
      ],
      "answer_count": 2,
      "accepted_answer_id": 10041779,
      "favorite_count": 0,
      "question_timeline_url": "/questions/9743550/timeline",
      "question_comments_url": "/questions/9743550/comments",
      "question_answers_url": "/questions/9743550/answers",
      "question_id": 9743550,
      "owner": {
        "user_id": 21728,
        "user_type": "registered",
        "display_name": "Borek",
        "reputation": 3561,
        "email_hash": "6159f200faa885e622ad3f5a288a44ac"
      },
      "creation_date": 1331927046,
      "last_activity_date": 1372773133,
      "up_vote_count": 10,
      "down_vote_count": 0,
      "view_count": 2560,
      "score": 10,
      "community_owned": false,
      "title": "IIS Express is automatically disabling anonymous authentication for my project, why?"
    },
    {
      "tags": [
        "jquery",
        "css",
        "div",
        "stylesheet"
      ],
      "answer_count": 2,
      "accepted_answer_id": 17427317,
      "favorite_count": 0,
      "question_timeline_url": "/questions/17427265/timeline",
      "question_comments_url": "/questions/17427265/comments",
      "question_answers_url": "/questions/17427265/answers",
      "question_id": 17427265,
      "owner": {
        "user_id": 1809053,
        "user_type": "registered",
        "display_name": "Andrew",
        "reputation": 106,
        "email_hash": "c4fe227e45a238bd50a244cd23c500c4"
      },
      "creation_date": 1372772663,
      "last_activity_date": 1372773133,
      "up_vote_count": 0,
      "down_vote_count": 0,
      "view_count": 38,
      "score": 0,
      "community_owned": false,
      "title": "Scrolling items in DIV horizontally instead of vertically?"
    },
    {
      "tags": [
        "asp.net",
        "hibernate",
        "nhibernate",
        "fluent-nhibernate"
      ],
      "answer_count": 0,
      "favorite_count": 0,
      "question_timeline_url": "/questions/17413450/timeline",
      "question_comments_url": "/questions/17413450/comments",
      "question_answers_url": "/questions/17413450/answers",
      "question_id": 17413450,
      "owner": {
        "user_id": 303468,
        "user_type": "registered",
        "display_name": "md1337",
        "reputation": 493,
        "email_hash": "938e5f30981c2571f6031a3de182ea02"
      },
      "creation_date": 1372711807,
      "last_edit_date": 1372773131,
      "last_activity_date": 1372773131,
      "up_vote_count": 0,
      "down_vote_count": 0,
      "view_count": 18,
      "score": 0,
      "community_owned": false,
      "title": "Using enums and native queries in NHibernate"
    },
    {
      "tags": [
        "objective-c",
        "nsstring"
      ],
      "answer_count": 2,
      "accepted_answer_id": 17427184,
      "favorite_count": 0,
      "closed_date": 1372843563,
      "closed_reason": "",
      "question_timeline_url": "/questions/17426658/timeline",
      "question_comments_url": "/questions/17426658/comments",
      "question_answers_url": "/questions/17426658/answers",
      "question_id": 17426658,
      "owner": {
        "user_id": 2465930,
        "user_type": "registered",
        "display_name": "Pawan Joshi",
        "reputation": 4,
        "email_hash": "65ff783a6a0459aeed7b9fa04882890d"
      },
      "creation_date": 1372770970,
      "last_edit_date": 1372771332,
      "last_activity_date": 1372773127,
      "up_vote_count": 1,
      "down_vote_count": 7,
      "view_count": 52,
      "score": -6,
      "community_owned": false,
      "title": "How to remove common letters in two Strings in iOS SDK?"
    },
    {
      "tags": [
        "css",
        "sass",
        "media-queries",
        "output"
      ],
      "answer_count": 1,
      "favorite_count": 0,
      "question_timeline_url": "/questions/17422843/timeline",
      "question_comments_url": "/questions/17422843/comments",
      "question_answers_url": "/questions/17422843/answers",
      "question_id": 17422843,
      "owner": {
        "user_id": 2542092,
        "user_type": "registered",
        "display_name": "Dean",
        "reputation": 6,
        "email_hash": "fb11047de0d34ae8a142ebba50f18b40"
      },
      "creation_date": 1372759733,
      "last_activity_date": 1372773123,
      "up_vote_count": 1,
      "down_vote_count": 0,
      "view_count": 32,
      "score": 1,
      "community_owned": false,
      "title": "scss output separate files"
    },
    {
      "tags": [
        "c++",
        "linear-algebra"
      ],
      "answer_count": 4,
      "accepted_answer_id": 2474558,
      "favorite_count": 0,
      "closed_date": 1347363033,
      "closed_reason": "not constructive",
      "question_timeline_url": "/questions/2474432/timeline",
      "question_comments_url": "/questions/2474432/comments",
      "question_answers_url": "/questions/2474432/answers",
      "question_id": 2474432,
      "owner": {
        "user_id": 89812,
        "user_type": "registered",
        "display_name": "Archagon",
        "reputation": 498,
        "email_hash": "edc075548433b37ac22857d02118034c"
      },
      "creation_date": 1268961776,
      "last_activity_date": 1372773117,
      "up_vote_count": 10,
      "down_vote_count": 0,
      "view_count": 6081,
      "score": 10,
      "community_owned": false,
      "title": "System of linear equations in C++?"
    },
    {
      "tags": [
        "vim",
        "latex"
      ],
      "answer_count": 0,
      "favorite_count": 0,
      "question_timeline_url": "/questions/17427420/timeline",
      "question_comments_url": "/questions/17427420/comments",
      "question_answers_url": "/questions/17427420/answers",
      "question_id": 17427420,
      "owner": {
        "user_id": 1638423,
        "user_type": "registered",
        "display_name": "joefromct",
        "reputation": 79,
        "email_hash": "9f91e24e2209a90b3f45dfc5f4e0b4c9"
      },
      "creation_date": 1372773110,
      "last_activity_date": 1372773110,
      "up_vote_count": 0,
      "down_vote_count": 0,
      "view_count": 13,
      "score": 0,
      "community_owned": false,
      "title": "Vim and Latex-Suite - Syntax turns off after compile?"
    },
    {
      "tags": [
        "java",
        "eclipse",
        "templates",
        "content-assist"
      ],
      "answer_count": 1,
      "favorite_count": 0,
      "question_timeline_url": "/questions/17424469/timeline",
      "question_comments_url": "/questions/17424469/comments",
      "question_answers_url": "/questions/17424469/answers",
      "question_id": 17424469,
      "owner": {
        "user_id": 1447326,
        "user_type": "registered",
        "display_name": "dstronczak",
        "reputation": 453,
        "email_hash": "32c1573004bc6e126ce9f9d6c03eb566"
      },
      "creation_date": 1372764684,
      "last_edit_date": 1372765271,
      "last_activity_date": 1372773103,
      "up_vote_count": 2,
      "down_vote_count": 0,
      "view_count": 22,
      "score": 2,
      "community_owned": false,
      "title": "Eclipse custom hotkey - print current line to standard out"
    },
    {
      "tags": [
        "jquery",
        "jquery-ajax"
      ],
      "answer_count": 1,
      "favorite_count": 0,
      "question_timeline_url": "/questions/17427311/timeline",
      "question_comments_url": "/questions/17427311/comments",
      "question_answers_url": "/questions/17427311/answers",
      "question_id": 17427311,
      "owner": {
        "user_id": 2027960,
        "user_type": "registered",
        "display_name": "UniqueChar",
        "reputation": 40,
        "email_hash": "a88be62f806381112b1fe143753e7fea"
      },
      "creation_date": 1372772810,
      "last_activity_date": 1372773097,
      "up_vote_count": 0,
      "down_vote_count": 0,
      "view_count": 19,
      "score": 0,
      "community_owned": false,
      "title": "AJAX Post stops other application events to fire"
    },
    {
      "tags": [
        "java",
        "criteria",
        "eclipselink",
        "jpa-2.0",
        "hibernate-criteria"
      ],
      "answer_count": 2,
      "accepted_answer_id": 4591615,
      "favorite_count": 3,
      "question_timeline_url": "/questions/4580285/timeline",
      "question_comments_url": "/questions/4580285/comments",
      "question_answers_url": "/questions/4580285/answers",
      "question_id": 4580285,
      "owner": {
        "user_id": 114804,
        "user_type": "registered",
        "display_name": "Gaim",
        "reputation": 2165,
        "email_hash": "cc1741ee1f11a2340aa1d54d21562959"
      },
      "creation_date": 1293999251,
      "last_edit_date": 1293999487,
      "last_activity_date": 1372773095,
      "up_vote_count": 12,
      "down_vote_count": 0,
      "view_count": 6902,
      "score": 12,
      "community_owned": false,
      "title": "JPA2: Case-insensitive like matching anywhere"
    },
    {
      "tags": [
        "c#",
        "active-directory",
        "dns",
        "comexception"
      ],
      "answer_count": 2,
      "accepted_answer_id": 4249412,
      "favorite_count": 8,
      "question_timeline_url": "/questions/4249139/timeline",
      "question_comments_url": "/questions/4249139/comments",
      "question_answers_url": "/questions/4249139/answers",
      "question_id": 4249139,
      "owner": {
        "user_id": 516534,
        "user_type": "registered",
        "display_name": "ghost_mv",
        "reputation": 474,
        "email_hash": "0a2eb057a7b096ca8e078aa3c5f007f2"
      },
      "creation_date": 1290452334,
      "last_edit_date": 1290462985,
      "last_activity_date": 1372773093,
      "up_vote_count": 12,
      "down_vote_count": 0,
      "view_count": 19284,
      "score": 12,
      "community_owned": false,
      "title": "C# Active Directory: Get domain name of user?"
    },
    {
      "tags": [
        "javascript",
        "jquery",
        "d3.js"
      ],
      "answer_count": 1,
      "accepted_answer_id": 17420935,
      "favorite_count": 0,
      "question_timeline_url": "/questions/17419270/timeline",
      "question_comments_url": "/questions/17419270/comments",
      "question_answers_url": "/questions/17419270/answers",
      "question_id": 17419270,
      "owner": {
        "user_id": 2357697,
        "user_type": "registered",
        "display_name": "Ash",
        "reputation": 54,
        "email_hash": "cf875729f1b501a332bba0dda8444c1f"
      },
      "creation_date": 1372748149,
      "last_edit_date": 1372772618,
      "last_activity_date": 1372773092,
      "up_vote_count": 0,
      "down_vote_count": 0,
      "view_count": 79,
      "score": 0,
      "community_owned": false,
      "title": "Adding the .attr() to a variable - Jquery"
    },
    {
      "tags": [
        "python",
        "django",
        "celery"
      ],
      "answer_count": 0,
      "favorite_count": 0,
      "question_timeline_url": "/questions/17427414/timeline",
      "question_comments_url": "/questions/17427414/comments",
      "question_answers_url": "/questions/17427414/answers",
      "question_id": 17427414,
      "owner": {
        "user_id": 514919,
        "user_type": "registered",
        "display_name": "Pratik Mandrekar",
        "reputation": 1788,
        "email_hash": "2a5f10090121269b40fd08b99ae4560f"
      },
      "creation_date": 1372773090,
      "last_activity_date": 1372773090,
      "up_vote_count": 0,
      "down_vote_count": 0,
      "view_count": 29,
      "score": 0,
      "community_owned": false,
      "title": "Celery Worker is offline"
    },
    {
      "tags": [
        "qt",
        "qgraphicsitem",
        "qgraphicsscene",
        "qgraphicstextitem"
      ],
      "answer_count": 1,
      "accepted_answer_id": 17427408,
      "favorite_count": 0,
      "question_timeline_url": "/questions/17425710/timeline",
      "question_comments_url": "/questions/17425710/comments",
      "question_answers_url": "/questions/17425710/answers",
      "question_id": 17425710,
      "owner": {
        "user_id": 848068,
        "user_type": "registered",
        "display_name": "saeed",
        "reputation": 933,
        "email_hash": "d893b452ce68913eb1e622bfcd4d7dc0"
      },
      "creation_date": 1372768224,
      "last_activity_date": 1372773076,
      "up_vote_count": 0,
      "down_vote_count": 0,
      "view_count": 15,
      "score": 0,
      "community_owned": false,
      "title": "How to save QGraphicsScene items to a .dxf file"
    },
    {
      "tags": [
        "javascript",
        "jquery-ajax"
      ],
      "answer_count": 4,
      "favorite_count": 0,
      "question_timeline_url": "/questions/17426678/timeline",
      "question_comments_url": "/questions/17426678/comments",
      "question_answers_url": "/questions/17426678/answers",
      "question_id": 17426678,
      "owner": {
        "user_id": 2541549,
        "user_type": "registered",
        "display_name": "Jarno",
        "reputation": 6,
        "email_hash": "61fe62c675e6480a8ef816afebbdbdd2"
      },
      "creation_date": 1372771035,
      "last_edit_date": 1372773073,
      "last_activity_date": 1372773073,
      "up_vote_count": 0,
      "down_vote_count": 0,
      "view_count": 70,
      "score": 0,
      "community_owned": false,
      "title": "If clause not working, every time falls to else part"
    },
    {
      "tags": [
        "titanium",
        "appcelerator",
        "appcelerator-mobile",
        "titanium-modules",
        "deezer"
      ],
      "answer_count": 0,
      "favorite_count": 0,
      "question_timeline_url": "/questions/17427404/timeline",
      "question_comments_url": "/questions/17427404/comments",
      "question_answers_url": "/questions/17427404/answers",
      "question_id": 17427404,
      "owner": {
        "user_id": 1460529,
        "user_type": "registered",
        "display_name": "Dario Rusignuolo",
        "reputation": 110,
        "email_hash": "8999f9bda37b1672a8e3591a191cc103"
      },
      "creation_date": 1372773062,
      "last_activity_date": 1372773062,
      "up_vote_count": 0,
      "down_vote_count": 0,
      "view_count": 25,
      "score": 0,
      "community_owned": false,
      "title": "deezer titanium appcelerator module"
    },
    {
      "tags": [
        "javascript",
        "rest",
        "sharepoint",
        "sharepoint2013",
        "client-object-model"
      ],
      "answer_count": 0,
      "favorite_count": 0,
      "question_timeline_url": "/questions/17427403/timeline",
      "question_comments_url": "/questions/17427403/comments",
      "question_answers_url": "/questions/17427403/answers",
      "question_id": 17427403,
      "owner": {
        "user_id": 1106360,
        "user_type": "registered",
        "display_name": "Rishi Jagati",
        "reputation": 20,
        "email_hash": "619ca6af10f50d554cccf9a26bc3ecf1"
      },
      "creation_date": 1372773062,
      "last_activity_date": 1372773062,
      "up_vote_count": 0,
      "down_vote_count": 0,
      "view_count": 31,
      "score": 0,
      "community_owned": false,
      "title": "How to pass large data from web page to SharePoint 2013 list using REST api - POST method?"
    },
    {
      "tags": [
        "windows",
        "visual-studio-2012"
      ],
      "answer_count": 1,
      "favorite_count": 0,
      "question_timeline_url": "/questions/16075171/timeline",
      "question_comments_url": "/questions/16075171/comments",
      "question_answers_url": "/questions/16075171/answers",
      "question_id": 16075171,
      "owner": {
        "user_id": 1967890,
        "user_type": "registered",
        "display_name": "user1967890",
        "reputation": 23,
        "email_hash": "07d696ceebce192fe21063004aaa1c3d"
      },
      "creation_date": 1366263122,
      "last_edit_date": 1366263947,
      "last_activity_date": 1372773059,
      "up_vote_count": 0,
      "down_vote_count": 0,
      "view_count": 120,
      "score": 0,
      "community_owned": false,
      "title": "how can i compile for windows XP with Virtual Studio 11.0 command prompt"
    },
    {
      "tags": [
        "python",
        "django",
        "query"
      ],
      "answer_count": 1,
      "accepted_answer_id": 17427401,
      "favorite_count": 0,
      "question_timeline_url": "/questions/17427098/timeline",
      "question_comments_url": "/questions/17427098/comments",
      "question_answers_url": "/questions/17427098/answers",
      "question_id": 17427098,
      "owner": {
        "user_id": 657183,
        "user_type": "registered",
        "display_name": "Deomachus",
        "reputation": 30,
        "email_hash": "6150d35563ac68679022dcc08432bee9"
      },
      "creation_date": 1372772236,
      "last_activity_date": 1372773058,
      "up_vote_count": 0,
      "down_vote_count": 0,
      "view_count": 27,
      "score": 0,
      "community_owned": false,
      "title": "Django Query - Retrieving associated foreign keys"
    },
    {
      "tags": [
        "uml",
        "software-engineering",
        "software-tools",
        "uml-modeling",
        "software-design"
      ],
      "answer_count": 1,
      "favorite_count": 1,
      "question_timeline_url": "/questions/17396594/timeline",
      "question_comments_url": "/questions/17396594/comments",
      "question_answers_url": "/questions/17396594/answers",
      "question_id": 17396594,
      "owner": {
        "user_id": 744616,
        "user_type": "registered",
        "display_name": "pranitkothari",
        "reputation": 107,
        "email_hash": "4d5a1d4ba48122bcddd239a84b8bf3e8"
      },
      "creation_date": 1372644541,
      "last_edit_date": 1372682521,
      "last_activity_date": 1372773057,
      "up_vote_count": 2,
      "down_vote_count": 0,
      "view_count": 32,
      "score": 2,
      "community_owned": false,
      "title": "How to get feedback on design"
    },
    {
      "tags": [
        "backbone.js",
        "mustache.js"
      ],
      "answer_count": 0,
      "favorite_count": 0,
      "question_timeline_url": "/questions/17427398/timeline",
      "question_comments_url": "/questions/17427398/comments",
      "question_answers_url": "/questions/17427398/answers",
      "question_id": 17427398,
      "owner": {
        "user_id": 1803557,
        "user_type": "registered",
        "display_name": "Khalid Dabjan",
        "reputation": 58,
        "email_hash": "1d2a6b642688d738618fb5e37c013043"
      },
      "creation_date": 1372773045,
      "last_activity_date": 1372773045,
      "up_vote_count": 0,
      "down_vote_count": 0,
      "view_count": 10,
      "score": 0,
      "community_owned": false,
      "title": "prevent Mustache from loading template from cache"
    },
    {
      "tags": [
        "cocoa",
        "uti"
      ],
      "answer_count": 1,
      "accepted_answer_id": 13049148,
      "favorite_count": 1,
      "question_timeline_url": "/questions/13046730/timeline",
      "question_comments_url": "/questions/13046730/comments",
      "question_answers_url": "/questions/13046730/answers",
      "question_id": 13046730,
      "owner": {
        "user_id": 34540,
        "user_type": "registered",
        "display_name": "Sophistifunk",
        "reputation": 1206,
        "email_hash": "a679d97760730f970749532b6e5abcb5"
      },
      "creation_date": 1351072137,
      "last_activity_date": 1372773044,
      "up_vote_count": 1,
      "down_vote_count": 0,
      "view_count": 63,
      "score": 1,
      "community_owned": false,
      "title": "Does Cocoa (AppKit) provide constants for standard UTIs?"
    },
    {
      "tags": [
        "magento",
        "acrobat"
      ],
      "answer_count": 3,
      "accepted_answer_id": 9634956,
      "favorite_count": 0,
      "question_timeline_url": "/questions/9634869/timeline",
      "question_comments_url": "/questions/9634869/comments",
      "question_answers_url": "/questions/9634869/answers",
      "question_id": 9634869,
      "owner": {
        "user_id": 649489,
        "user_type": "registered",
        "display_name": "Gas",
        "reputation": 59,
        "email_hash": "910b1b107b37c0d3b79ab3f21ad697cf"
      },
      "creation_date": 1331299926,
      "last_activity_date": 1372773037,
      "up_vote_count": 0,
      "down_vote_count": 0,
      "view_count": 1184,
      "score": 0,
      "community_owned": false,
      "title": "Outside link for Add to Cart"
    },
    {
      "tags": [
        "android"
      ],
      "answer_count": 0,
      "favorite_count": 0,
      "question_timeline_url": "/questions/17427210/timeline",
      "question_comments_url": "/questions/17427210/comments",
      "question_answers_url": "/questions/17427210/answers",
      "question_id": 17427210,
      "owner": {
        "user_id": 2542756,
        "user_type": "registered",
        "display_name": "user2542756",
        "reputation": 1,
        "email_hash": "5f09bdc66a252f90ea0c4809b441ec5d"
      },
      "creation_date": 1372772508,
      "last_edit_date": 1372773032,
      "last_activity_date": 1372773032,
      "up_vote_count": 0,
      "down_vote_count": 3,
      "view_count": 45,
      "score": -3,
      "community_owned": false,
      "title": "Emulator crashing"
    },
    {
      "tags": [
        "jquery",
        "jquery-select2"
      ],
      "answer_count": 0,
      "favorite_count": 0,
      "question_timeline_url": "/questions/17427394/timeline",
      "question_comments_url": "/questions/17427394/comments",
      "question_answers_url": "/questions/17427394/answers",
      "question_id": 17427394,
      "owner": {
        "user_id": 22113,
        "user_type": "registered",
        "display_name": "Gary",
        "reputation": 442,
        "email_hash": "827f06c9c34f7b05959702be8b30d0fe"
      },
      "creation_date": 1372773032,
      "last_activity_date": 1372773032,
      "up_vote_count": 0,
      "down_vote_count": 0,
      "view_count": 23,
      "score": 0,
      "community_owned": false,
      "title": "Assign dynamic options to select2 plugin constructor"
    },
    {
      "tags": [
        "python"
      ],
      "answer_count": 12,
      "accepted_answer_id": 431715,
      "favorite_count": 21,
      "question_timeline_url": "/questions/431684/timeline",
      "question_comments_url": "/questions/431684/comments",
      "question_answers_url": "/questions/431684/answers",
      "question_id": 431684,
      "owner": {
        "user_id": 28835,
        "user_type": "registered",
        "display_name": "too much php",
        "reputation": 21946,
        "email_hash": "34a7a029578b79cf4afa596ad4e3e72b"
      },
      "creation_date": 1231619296,
      "last_edit_date": 1231623735,
      "last_activity_date": 1372773024,
      "up_vote_count": 92,
      "down_vote_count": 0,
      "view_count": 94834,
      "score": 92,
      "community_owned": false,
      "title": "How do I \"cd\" in python"
    }
  ]
}
